heroku_manager/__init__.py
heroku_manager/heroku.py
heroku_manager-0.1.0.dist-info/METADATA
heroku_manager-0.1.0.dist-info/WHEEL
heroku_manager-0.1.0.dist-info/top_level.txt
heroku_manager-0.1.0.dist-info/RECORD
