Metadata-Version: 2.2
Name: heroku_manager
Version: 0.1.0
Summary: A package for managing Heroku dynos with autoscaling capabilities
Home-page: https://github.com/floship/heroku-manager
Author: Floship
Author-email: stas@floship.com
Classifier: Programming Language :: Python :: 3
Classifier: License :: OSI Approved :: MIT License
Classifier: Operating System :: OS Independent
Requires-Python: >=3.6
Requires-Dist: django>=2.2
Requires-Dist: requests>=2.0.0
Requires-Dist: tenacity>=6.0.0
Dynamic: author
Dynamic: author-email
Dynamic: classifier
Dynamic: description
Dynamic: description-content-type
Dynamic: home-page
Dynamic: requires-dist
Dynamic: requires-python
Dynamic: summary
